cLoops2/__init__.py
cLoops2/agg.py
cLoops2/ano.py
cLoops2/blockDBSCAN.py
cLoops2/cDBSCAN2.py
cLoops2/cLoops2.py
cLoops2/callCisLoops.py
cLoops2/callDiffLoops.py
cLoops2/callDomains.py
cLoops2/callPeaks.py
cLoops2/callTransLoops.py
cLoops2/cmat.py
cLoops2/comp.py
cLoops2/ds.py
cLoops2/dump.py
cLoops2/est.py
cLoops2/estDis.py
cLoops2/estSim.py
cLoops2/filter.py
cLoops2/findTargets.py
cLoops2/geo.py
cLoops2/io.py
cLoops2/montage.py
cLoops2/norm.py
cLoops2/plot.py
cLoops2/qc.py
cLoops2/quant.py
cLoops2/settings.py
cLoops2/stat.py
cLoops2/utils.py
cLoops2-0.0.3.data/scripts/getBedpeFBed.py
cLoops2-0.0.3.data/scripts/getDI.py
cLoops2-0.0.3.data/scripts/getFRiF.py
cLoops2-0.0.3.data/scripts/getIS.py
cLoops2-0.0.3.data/scripts/getIntDensity.py
cLoops2-0.0.3.data/scripts/getLocalIDS.py
cLoops2-0.0.3.data/scripts/getPETsAno.py
cLoops2-0.0.3.data/scripts/getSigDist.py
cLoops2-0.0.3.data/scripts/getSigEnrich.py
cLoops2-0.0.3.data/scripts/hicpro2bedpe.py
cLoops2-0.0.3.data/scripts/juicerLong2bedpe.py
cLoops2-0.0.3.data/scripts/mergeDomains.py
cLoops2-0.0.3.data/scripts/plotDiffHeatmap.py
cLoops2-0.0.3.data/scripts/tow.py
cLoops2-0.0.3.data/scripts/tracPre.py
cLoops2-0.0.3.data/scripts/tracPre2.py
cLoops2-0.0.3.dist-info/LICENSE
cLoops2-0.0.3.dist-info/METADATA
cLoops2-0.0.3.dist-info/WHEEL
cLoops2-0.0.3.dist-info/entry_points.txt
cLoops2-0.0.3.dist-info/top_level.txt
cLoops2-0.0.3.dist-info/RECORD
