Metadata-Version: 2.1
Name: cLoops2
Version: 0.0.3
Summary: Loop-calling and peak-calling for sequencing-based interaction data, including related analysis utilities.
Home-page: https://github.com/YaqiangCao/cLoops2
Author: Yaqiang Cao
Author-email: caoyaqiang0410@gmail.com
License: UNKNOWN
Project-URL: Source, https://github.com/YaqiangCao/cLoops2
Keywords: peak-calling loop-calling Hi-Trac interaction visualization
Platform: UNKNOWN
Classifier: Environment :: Console
Classifier: Operating System :: MacOS :: MacOS X
Classifier: Operating System :: POSIX
Classifier: Topic :: Scientific/Engineering :: Bio-Informatics
Requires-Python: >=3
Requires-Dist: joblib
Requires-Dist: numpy
Requires-Dist: seaborn
Requires-Dist: pandas
Requires-Dist: scipy
Requires-Dist: scikit-learn
Requires-Dist: matplotlib
Requires-Dist: tqdm
Requires-Dist: pyBigWig
Requires-Dist: networkx
